pyangbind/__init__.py
pyangbind/helpers/__init__.py
pyangbind/helpers/identity.py
pyangbind/helpers/misc.py
pyangbind/lib/__init__.py
pyangbind/lib/base.py
pyangbind/lib/pybindJSON.py
pyangbind/lib/serialise.py
pyangbind/lib/xpathhelper.py
pyangbind/lib/yangtypes.py
pyangbind/plugin/pybind.py
pyangbind_brcd-0.6.14.dist-info/DESCRIPTION.rst
pyangbind_brcd-0.6.14.dist-info/METADATA
pyangbind_brcd-0.6.14.dist-info/RECORD
pyangbind_brcd-0.6.14.dist-info/WHEEL
pyangbind_brcd-0.6.14.dist-info/metadata.json
pyangbind_brcd-0.6.14.dist-info/top_level.txt
