Metadata-Version: 2.0
Name: pyangbind-brcd
Version: 0.6.14
Summary: PyangBind is a plugin for pyang which converts YANG datamodels into a Python class hierarchy, such that Python can be used to manipulate data that conforms with a YANG model.
Home-page: https://github.com/StackStorm/pyangbind
Author: Rob Shakir
Author-email: rjs@rob.sh
License: Apache
Keywords: yang pyang
Platform: UNKNOWN
Classifier: Development Status :: 4 - Beta
Classifier: Intended Audience :: Telecommunications Industry
Classifier: Intended Audience :: Developers
Classifier: Topic :: Software Development :: Code Generators
Classifier: License :: OSI Approved :: Apache Software License
Classifier: Programming Language :: Python :: 2.7
Classifier: Programming Language :: Python :: 2 :: Only
Requires-Dist: bitarray
Requires-Dist: lxml
Requires-Dist: pyang
